pyartifact/.DS_Store
pyartifact/__init__.py
pyartifact/_context.py
pyartifact/api_sync.py
pyartifact/deck.py
pyartifact/deck_encoding/__init__.py
pyartifact/deck_encoding/decode.py
pyartifact/deck_encoding/encode.py
pyartifact/exceptions.py
pyartifact/filtering.py
pyartifact/sets_and_cards.py
pyartifact/types/.DS_Store
pyartifact/types/__init__.py
pyartifact/types/deck_types.py
pyartifact/types/json_types.py
pyartifact-0.3.2.dist-info/LICENSE
pyartifact-0.3.2.dist-info/WHEEL
pyartifact-0.3.2.dist-info/METADATA
pyartifact-0.3.2.dist-info/RECORD
